<?xml version="1.0" encoding="UTF-8" standalone="no"?>
<batch>
  <entities>
    <ref_nokbdb>
      <code>J:КИК:</code>
    </ref_nokbdb>
    <ref_nokbdb>
      <code>J:Элитстрой Финанс:</code>
    </ref_nokbdb>
    <ref_nokbdb>
      <code>J:АлмРегИпотечОрг:</code>
    </ref_nokbdb>
    <ref_nokbdb>
      <code>J:Агр КредКорп:</code>
    </ref_nokbdb>
    <ref_nokbdb>
      <code>J:КазАгроФин:</code>
    </ref_nokbdb>
    <ref_nokbdb>
      <code>J:Фонд ФПСХ:</code>
    </ref_nokbdb>
    <ref_nokbdb>
      <code>J:ПродКонтрактКорп:</code>
    </ref_nokbdb>
    <ref_nokbdb>
      <code>J600900577988Ипотечная :</code>
    </ref_nokbdb>
  </entities>
</batch>
